techchallenge_summarizer/__init__.py
techchallenge_summarizer/main.py
techchallenge_summarizer/prompts.py
techchallenge_summarizer-2025.12.21164129.dist-info/METADATA
techchallenge_summarizer-2025.12.21164129.dist-info/WHEEL
techchallenge_summarizer-2025.12.21164129.dist-info/top_level.txt
techchallenge_summarizer-2025.12.21164129.dist-info/RECORD
