Metadata-Version: 2.4
Name: techchallenge-summarizer
Version: 2025.12.21164129
Summary: A new package that processes user-provided text input to generate structured summaries of technical challenges, such as the difficulty of implementing resumable LLM streaming. It uses a system prompt
Author-email: techchallenge-summarizer <hi@eugene.plus>
License: MIT
Project-URL: Homepage, https://github.com/chigwell/techchallenge-summarizer
Requires-Python: >=3.9
Requires-Dist: langchain-llm7>=0.0.0
Requires-Dist: llmatch-messages>=0.0.0
Requires-Dist: langchain-core>=0.3.0
